sphinx_thunlp_theme/__init__.py
sphinx_thunlp_theme/footer.html
sphinx_thunlp_theme/header.html
sphinx_thunlp_theme/layout.html
sphinx_thunlp_theme/search.html
sphinx_thunlp_theme/searchbox.html
sphinx_thunlp_theme/theme.conf
sphinx_thunlp_theme/static/css/home.css
sphinx_thunlp_theme/static/css/page.css
sphinx_thunlp_theme/static/css/theme.css
sphinx_thunlp_theme/static/fonts/light.otf
sphinx_thunlp_theme/static/fonts/regular.otf
sphinx_thunlp_theme/static/images/facebook.svg
sphinx_thunlp_theme/static/images/github.svg
sphinx_thunlp_theme/static/images/twitter.svg
sphinx_thunlp_theme/static/images/wechat.svg
sphinx_thunlp_theme/static/images/weibo.svg
sphinx_thunlp_theme/static/images/wx_qrcode.jpg
sphinx_thunlp_theme/static/js/page.js
sphinx_thunlp_theme/static/js/theme.js
sphinx_thunlp_theme-0.0.9.dist-info/METADATA
sphinx_thunlp_theme-0.0.9.dist-info/WHEEL
sphinx_thunlp_theme-0.0.9.dist-info/entry_points.txt
sphinx_thunlp_theme-0.0.9.dist-info/top_level.txt
sphinx_thunlp_theme-0.0.9.dist-info/RECORD
