Metadata-Version: 2.1
Name: sphinx-thunlp-theme
Version: 0.0.9
Summary: THUNLP open-source project theme for Sphinx
Home-page: https://github.com/a710128/sphinx_thunlp_docs
Author: a710128
Author-email: qbjooo@qq.com
License: MIT
Platform: UNKNOWN
Classifier: Framework :: Sphinx
Classifier: Framework :: Sphinx :: Theme
Classifier: Development Status :: 3 - Alpha
Classifier: License :: OSI Approved :: MIT License
Classifier: Environment :: Console
Classifier: Environment :: Web Environment
Classifier: Intended Audience :: Developers
Classifier: Programming Language :: Python :: 3
Classifier: Programming Language :: Python :: 3.6
Classifier: Programming Language :: Python :: 3.7
Classifier: Programming Language :: Python :: 3.8
Classifier: Programming Language :: Python :: 3.9
Classifier: Operating System :: OS Independent
Classifier: Topic :: Documentation
Classifier: Topic :: Software Development :: Documentation
Requires-Dist: sphinx (<4,>=3)
